tests/__init__.py
tests/test_altimetry_api.py
tests/test_dmi_api.py
watobs/__init__.py
watobs/altimetry.py
watobs/dmi.py
watobs-0.1.1.dist-info/METADATA
watobs-0.1.1.dist-info/WHEEL
watobs-0.1.1.dist-info/top_level.txt
watobs-0.1.1.dist-info/RECORD
