Metadata-Version: 2.1
Name: watobs
Version: 0.1.1
Summary: Access water observation data
Home-page: https://github.com/DHI/watobs
Author: Jesper Sandvig Mariegaard
Author-email: jem@dhigroup.com
License: MIT
Classifier: License :: OSI Approved :: MIT License
Classifier: Development Status :: 2 - Pre-Alpha
Classifier: Intended Audience :: Science/Research
Classifier: Programming Language :: Python
Classifier: Programming Language :: Python :: 3
Classifier: Operating System :: OS Independent
Classifier: Topic :: Scientific/Engineering
Requires-Dist: numpy
Requires-Dist: pandas
Requires-Dist: requests
Requires-Dist: matplotlib
Provides-Extra: dev
Requires-Dist: pytest; extra == "dev"
Requires-Dist: flake8; extra == "dev"
Requires-Dist: black; extra == "dev"
Requires-Dist: sphinx; extra == "dev"
Requires-Dist: myst-parser; extra == "dev"
Requires-Dist: sphinx-book-theme; extra == "dev"
Provides-Extra: notebooks
Requires-Dist: nbformat; extra == "notebooks"
Requires-Dist: nbconvert; extra == "notebooks"
Requires-Dist: jupyter; extra == "notebooks"
Requires-Dist: folium; extra == "notebooks"
Requires-Dist: rtree; extra == "notebooks"
Requires-Dist: mapclassify; extra == "notebooks"
Requires-Dist: geopandas; extra == "notebooks"
Requires-Dist: xarray; extra == "notebooks"
Requires-Dist: netcdf4; extra == "notebooks"
Requires-Dist: NDBC; extra == "notebooks"
Provides-Extra: test
Requires-Dist: pytest; extra == "test"
Requires-Dist: mikeio; extra == "test"
